[{
	"side": "R",
	"functions": [
		{"name": "XX", "style": "dummy"},
		{"name": "VIN", "style": "power"}]
},{
	"side": "R",
	"functions": [
		{"name": "XX", "style": "dummy"},
		{"name": "VBAT", "style": "power"}]
},{
	"side": "R",
	"functions": [
		{"name": "XX", "style": "dummy"},
		{"name": "GND", "style": "GND"}]
},{
	"side": "R",
	"isPWM": true,
	"functions": [
		{"name": "25", "style": "physicalPin"},
		{"name": "PB1", "style": "portPin"},

		{"name": "TIM3_CH4", "style": "timer", "category": "alternate"},
		{"name": "TIM8_CH3N", "style": "timer", "category": "alternate"},
		{"name": "TIM1_CH3N", "style": "timer", "category": "alternate"},
		{"name": "COMP4_OUT", "style": "analog", "category": "alternate"},
		{"name": "QUADSPI1_BK1_IO0", "style": "spi", "category": "alternate"},
		{"name": "LPUART1_RTS_DE", "style": "serial", "category": "alternate"},
		{"name": "HRTIM1_SCOUT", "style": "timer", "category": "alternate"},
		{"name": "EVENTOUT", "style": "hidden", "category": "alternate"},

		{"name": "ADC3_IN1/ADC1_IN12", "style": "analog", "category": "additional"},
		{"name": "COMP1+", "style": "analog", "category": "additional"},
		{"name": "OPAMP3_VOUT", "style": "analog", "category": "additional"},
		{"name": "OPAMP6_V-", "style": "analog", "category": "additional"}
	]
},{
	"side": "R",
	"functions": [
		{"name": "XX", "style": "dummy"},
		{"name": "+3V3", "style": "power"}
	]
},{
	"side": "R",
	"functions": [
		{"name": "22", "style": "physicalPin"},
		{"name": "PC4", "style": "portPin"},

		{"name": "TIM1_ETR", "style": "timer", "category": "alternate"},
		{"name": "I2C2_SCL", "style": "i2c", "category": "alternate"},
		{"name": "USART1_TX", "style": "serial", "category": "alternate"},
		{"name": "QUADSPI1_BK2_IO3", "style": "spi", "category": "alternate"},
		{"name": "EVENTOUT", "style": "hidden", "category": "alternate"},

		{"name": "ADC2_IN5", "style": "analog", "category": "additional"}
	]
},{
	"side": "R",
	"functions": [
		{"name": "20", "style": "physicalPin"},
		{"name": "PA6", "style": "portPin"},

		{"name": "TIM16_CH1", "style": "timer", "category": "alternate"},
		{"name": "TIM3_CH1", "style": "timer", "category": "alternate"},
		{"name": "TIM8_BKIN", "style": "timer", "category": "alternate"},
		{"name": "SPI1_MISO", "style": "spi", "category": "alternate"},
		{"name": "TIM1_BKIN", "style": "timer", "category": "alternate"},
		{"name": "COMP1_OUT", "style": "analog", "category": "alternate"},
		{"name": "QUADSPI1_BK1_IO3", "style": "spi", "category": "alternate"},
		{"name": "LPUART1_CTS", "style": "serial", "category": "alternate"},
		{"name": "EVENTOUT", "style": "hidden", "category": "alternate"},
		
		{"name": "ADC2_IN3", "style": "analog", "category": "additional"},
		{"name": "DAC2_OUT1", "style": "DAC", "category": "additional"},
		{"name": "OPAMP2_VOUT", "style": "analog", "category": "additional"}
	]
},{
	"side": "R",
	"functions": [
		{"name": "XX", "style": "dummy"},
		{"name": "GND", "style": "GND"}
	]
},{
	"side": "R",
	"functions": [
		{"name": "19", "style": "physicalPin"},
		{"name": "PA5", "style": "portPin"},
		{"name": "LED BUILTIN", "style": "led"},

		{"name": "TIM2_CH1", "style": "timer", "category": "alternate"},
		{"name": "TIM2_ETR", "style": "timer", "category": "alternate"},
		{"name": "SPI1_SCK", "style": "spi", "category": "alternate"},
		{"name": "UCPD1_FRSTX", "style": "usb", "category": "alternate"},
		{"name": "EVENTOUT", "style": "hidden", "category": "alternate"},

		{"name": "ADC2_IN13", "style": "analog", "category": "additional"},
		{"name": "DAC1_OUT2", "style": "DAC", "category": "additional"},
		{"name": "COMP2-", "style": "analog", "category": "additional"},
		{"name": "OPAMP2_V-", "style": "analog", "category": "additional"}
	]
},{
	"side": "R",
	"isPWM": true,
	"functions": [
		{"name": "24", "style": "physicalPin"},
		{"name": "PB0", "style": "portPin"},

		{"name": "TIM3_CH3", "style": "timer", "category": "alternate"},
		{"name": "TIM8_CH2N", "style": "timer", "category": "alternate"},
		{"name": "TIM1_CH2N", "style": "timer", "category": "alternate"},
		{"name": "QUADSPI1_BK1_IO1", "style": "spi", "category": "alternate"},
		{"name": "HRTIM1_FLT5", "style": "timer", "category": "alternate"},
		{"name": "UCPD1_FRSTX", "style": "usb", "category": "alternate"},
		{"name": "EVENTOUT", "style": "hidden", "category": "alternate"},
		
		{"name": "ADC3_IN12/ADC1_IN15", "style": "analog", "category": "additional"},
		{"name": "COMP4+", "style": "analog", "category": "additional"},
		{"name": "OPAMP2+", "style": "analog", "category": "additional"},
		{"name": "OPAMP3+", "style": "analog", "category": "additional"}
	]
},{
	"side": "R",
	"functions": [
		{"name": "13", "style": "physicalPin"},
		{"name": "PA1", "style": "portPin"},

		{"name": "RTC_REFIN", "style": "rtc", "category": "alternate"},
		{"name": "TIM2_CH2", "style": "timer", "category": "alternate"},
		{"name": "TIM5_CH2", "style": "timer", "category": "alternate"},
		{"name": "USART2_RTS_DE", "style": "serial", "category": "alternate"},
		{"name": "TIM15_CH1N", "style": "timer", "category": "alternate"},
		{"name": "EVENTOUT", "style": "hidden", "category": "alternate"},

		{"name": "ADC12 IN2", "style": "analog", "category": "additional"},
		{"name": "COMP1+", "style": "analog", "category": "additional"},
		{"name": "OPAMP1+", "style": "analog", "category": "additional"},
		{"name": "OPAMP3+", "style": "analog", "category": "additional"},
		{"name": "OPAMP6-", "style": "analog", "category": "additional"}
	]
},{
	"side": "R",
	"functions": [
		{"name": "12", "style": "physicalPin"},
		{"name": "PA0", "style": "portPin"},

		{"name": "TIM2_CH1", "style": "timer", "category": "alternate"},
		{"name": "TIM5_CH1", "style": "timer", "category": "alternate"},
		{"name": "USART2_CTS", "style": "serial", "category": "alternate"},
		{"name": "COMP1_OUT", "style": "analog", "category": "alternate"},
		{"name": "TIM8_BKIN", "style": "timer", "category": "alternate"},
		{"name": "TIM8_ETR", "style": "timer", "category": "alternate"},
		{"name": "TIM2_ETR", "style": "timer", "category": "alternate"},
		{"name": "EVENTOUT", "style": "hidden", "category": "alternate"},

		{"name": "ADC12 IN1", "style": "analog", "category": "additional"},
		{"name": "COMP1-", "style": "analog", "category": "additional"},
		{"name": "COMP3+", "style": "analog", "category": "additional"},
		{"name": "RTC_TAMP2", "style": "rtc", "category": "additional"},
		{"name": "WKUP1", "style": "control", "category": "additional"}
	]
},{
	"side": "R",
	"functions": [
		{"name": "XX", "style": "dummy"},
		{"name": "GND", "style": "GND"}
	]
},{
	"side": "R",
	"functions": [
		{"name": "11", "style": "physicalPin"},
		{"name": "PC3", "style": "portPin"},

		{"name": "LPTIM1_ETR", "style": "timer", "category": "alternate"},
		{"name": "TIM1_CH4", "style": "timer", "category": "alternate"},
		{"name": "SAI1_D1", "style": "audio", "category": "alternate"},
		{"name": "TIM1_BKIN2", "style": "timer", "category": "alternate"},
		{"name": "QUADSPI1_BK2_IO2", "style": "spi", "category": "alternate"},
		{"name": "SAI1_SD_A", "style": "audio", "category": "alternate"},
		{"name": "EVENTOUT", "style": "hidden", "category": "alternate"},
			
		{"name": "ADC12_IN9", "style": "analog", "category": "additional"},
		{"name": "OPAMP5_V+", "style": "analog", "category": "additional"}
	]
},{
	"side": "R",
	"functions": [
		{"name": "10", "style": "physicalPin"},
		{"name": "PC2", "style": "portPin"},

		{"name": "LPTIM1_IN2", "style": "timer", "category": "alternate"},
		{"name": "TIM1_CH3", "style": "timer", "category": "alternate"},
		{"name": "COMP3_OUT", "style": "analog", "category": "alternate"},
		{"name": "TIM20_CH2", "style": "timer", "category": "alternate"},
		{"name": "QUADSPI1_BK2_IO1", "style": "spi", "category": "alternate"},
		{"name": "EVENTOUT", "style": "hidden", "category": "alternate"},
		
		{"name": "ADC12_IN8", "style": "analog", "category": "additional"}
	]
},{
	"side": "R",
	"functions": [
		{"name": "9", "style": "physicalPin"},
		{"name": "PC1", "style": "portPin"},

		{"name": "LPTIM1_OUT", "style": "timer", "category": "alternate"},
		{"name": "TIM1_CH2", "style": "timer", "category": "alternate"},
		{"name": "LPUART1_TX", "style": "serial", "category": "alternate"},
		{"name": "QUADSPI1_BK2_IO0", "style": "spi", "category": "alternate"},
		{"name": "SAI1_SD_A", "style": "audio", "category": "alternate"},
		{"name": "EVENTOUT", "style": "hidden", "category": "alternate"},

		{"name": "ADC12_IN7", "style": "analog", "category": "additional"},
		{"name": "COMP3+", "style": "analog", "category": "additional"}
	]
},{
	"side": "R",
	"functions": [
		{"name": "8", "style": "physicalPin"},
		{"name": "PC0", "style": "portPin"},

		{"name": "LPTIM1_IN1", "style": "timer", "category": "alternate"},
		{"name": "TIM1_CH1", "style": "timer", "category": "alternate"},
		{"name": "LPUART1_RX", "style": "serial", "category": "alternate"},
		{"name": "EVENTOUT", "style": "hidden", "category": "alternate"},

		{"name": "ADC12_IN6", "style": "analog", "category": "additional"},
		{"name": "COMP3-", "style": "analog", "category": "additional"}
	]
},{
	"side": "R",
	"functions": [
		{"name": "XX", "style": "dummy"},
		{"name": "GND", "style": "GND"}]
},{
	"side": "R",
	"functions": [
		{"name": "2", "style": "physicalPin"},
		{"name": "PC13", "style": "portPin"},
		
		{"name": "TIM1_BKIN", "style": "timer", "category": "alternate"},
		{"name": "TIM1_CH1N", "style": "timer", "category": "alternate"},
		{"name": "TIM8_CH4N", "style": "timer", "category": "alternate"},
		{"name": "EVENTOUT", "style": "hidden", "category": "alternate"},

		{"name": "WKUP2", "style": "control", "category": "additional"},
		{"name": "RTC_TAMP1", "style": "rtc", "category": "additional"},
		{"name": "RTC_TS", "style": "rtc", "category": "additional"},
		{"name": "RTC_OUT1", "style": "rtc", "category": "additional"}
	]
},{
	"side": "R",
	"isPWM": true,
	"functions": [
		{"name": "62", "style": "physicalPin"},
		{"name": "PB9", "style": "portPin"},

		{"name": "TIM17_CH1", "style": "timer", "category": "alternate"},
		{"name": "TIM4_CH4", "style": "timer", "category": "alternate"},
		{"name": "SAI1_D2", "style": "audio", "category": "alternate"},
		{"name": "I2C1_SDA", "style": "i2c", "category": "alternate"},
		{"name": "IR_OUT", "style": "serial", "category": "alternate"}, 
		{"name": "USART3_TX", "style": "serial", "category": "alternate"},
		{"name": "COMP2_OUT", "style": "analog", "category": "alternate"},
		{"name": "FDCAN1_TX", "style": "serial", "category": "alternate"},
		{"name": "TIM8_CH3", "style": "timer", "category": "alternate"},
		{"name": "TIM1_CH3N", "style": "timer", "category": "alternate"},
		{"name": "HRTIM1_EEV5", "style": "timer", "category": "alternate"},
		{"name": "SAI1_FS_A", "style": "audio", "category": "alternate"},
		{"name": "EVENTOUT", "style": "hidden", "category": "alternate"}
	]
}]